pycounts_pcdlf/__init__.py
pycounts_pcdlf/plotting.py
pycounts_pcdlf/pycounts_pcdlf.py
pycounts_pcdlf-0.1.0.dist-info/LICENSE
pycounts_pcdlf-0.1.0.dist-info/METADATA
pycounts_pcdlf-0.1.0.dist-info/WHEEL
pycounts_pcdlf-0.1.0.dist-info/RECORD
