Metadata-Version: 2.1
Name: pycounts_pcdlf
Version: 0.1.0
Summary: First test package
License: MIT
Author: Peter de Looff
Requires-Python: >=3.11
Classifier: License :: OSI Approved :: MIT License
Classifier: Programming Language :: Python :: 3
Classifier: Programming Language :: Python :: 3.11
Classifier: Programming Language :: Python :: 3.12
Requires-Dist: matplotlib (>=3.8.2)
